LICENCE
README.md
setup.py
apollus_py_utils.egg-info/PKG-INFO
apollus_py_utils.egg-info/SOURCES.txt
apollus_py_utils.egg-info/dependency_links.txt
apollus_py_utils.egg-info/requires.txt
apollus_py_utils.egg-info/top_level.txt
database/__init__.py
database/apollus_db.py