Metadata-Version: 2.1
Name: apollus-py-utils
Version: 0.0.2
Summary: Funcoes Utils
Author: Fabiel Prestes
Author-email: fabiel.prestes@apollusehs.com.br
License: MIT License
Keywords: apollus
License-File: LICENCE
